pyxelext/__init__.py
pyxelext/input.py
pyxelext/line.py
pyxelext/physics.py
pyxelext/system.py
pyxelext/text.py
pyxelext/examples/1_draw_aline.py
pyxelext/examples/2_length_line.py
pyxelext/examples/3_poly.py
pyxelext/examples/4_getkey.py
pyxelext/examples/5_text.py
pyxelext/examples/6_static_rect.py
pyxelext/examples/7_system.py
pyxelext/examples/__init__.py
pyxelext-1.4.3.post3.dist-info/LICENSE
pyxelext-1.4.3.post3.dist-info/METADATA
pyxelext-1.4.3.post3.dist-info/WHEEL
pyxelext-1.4.3.post3.dist-info/top_level.txt
pyxelext-1.4.3.post3.dist-info/RECORD
