Metadata-Version: 2.1
Name: pyxelext
Version: 1.4.3.post3
Summary: UNKNOWN
Home-page: UNKNOWN
License: UNKNOWN
Platform: UNKNOWN
Requires-Dist: pyxel (>=1.4.3)
Provides-Extra: images
Requires-Dist: pillow ; extra == 'images'
Provides-Extra: physics
Requires-Dist: pymunk ; extra == 'physics'
